rfnetwork/__init__.py
rfnetwork/component.py
rfnetwork/elements.py
rfnetwork/netlist.py
rfnetwork/network.py
rfnetwork/plots.py
rfnetwork/touchstone.py
rfnetwork/tuning.py
rfnetwork/utils copy.py
rfnetwork/utils.py
rfnetwork/core/core.py
rfnetwork/core/core_func.cpython-312-x86_64-linux-gnu.so
rfnetwork/core/units.py
rfnetwork/core/inc/connect.h
rfnetwork/core/lib/eigen/Eigen/AccelerateSupport
rfnetwork/core/lib/eigen/Eigen/Cholesky
rfnetwork/core/lib/eigen/Eigen/CholmodSupport
rfnetwork/core/lib/eigen/Eigen/Core
rfnetwork/core/lib/eigen/Eigen/Dense
rfnetwork/core/lib/eigen/Eigen/Eigen
rfnetwork/core/lib/eigen/Eigen/Eigenvalues
rfnetwork/core/lib/eigen/Eigen/Geometry
rfnetwork/core/lib/eigen/Eigen/Householder
rfnetwork/core/lib/eigen/Eigen/IterativeLinearSolvers
rfnetwork/core/lib/eigen/Eigen/Jacobi
rfnetwork/core/lib/eigen/Eigen/KLUSupport
rfnetwork/core/lib/eigen/Eigen/LU
rfnetwork/core/lib/eigen/Eigen/MetisSupport
rfnetwork/core/lib/eigen/Eigen/OrderingMethods
rfnetwork/core/lib/eigen/Eigen/PaStiXSupport
rfnetwork/core/lib/eigen/Eigen/PardisoSupport
rfnetwork/core/lib/eigen/Eigen/QR
rfnetwork/core/lib/eigen/Eigen/QtAlignedMalloc
rfnetwork/core/lib/eigen/Eigen/SPQRSupport
rfnetwork/core/lib/eigen/Eigen/SVD
rfnetwork/core/lib/eigen/Eigen/Sparse
rfnetwork/core/lib/eigen/Eigen/SparseCholesky
rfnetwork/core/lib/eigen/Eigen/SparseCore
rfnetwork/core/lib/eigen/Eigen/SparseLU
rfnetwork/core/lib/eigen/Eigen/SparseQR
rfnetwork/core/lib/eigen/Eigen/StdDeque
rfnetwork/core/lib/eigen/Eigen/StdList
rfnetwork/core/lib/eigen/Eigen/StdVector
rfnetwork/core/lib/eigen/Eigen/SuperLUSupport
rfnetwork/core/lib/eigen/Eigen/ThreadPool
rfnetwork/core/lib/eigen/Eigen/UmfPackSupport
rfnetwork/core/lib/eigen/Eigen/src/AccelerateSupport/AccelerateSupport.h
rfnetwork/core/lib/eigen/Eigen/src/AccelerateSupport/InternalHeaderCheck.h
rfnetwork/core/lib/eigen/Eigen/src/Cholesky/InternalHeaderCheck.h
rfnetwork-0.1.1.dist-info/METADATA
rfnetwork-0.1.1.dist-info/WHEEL
rfnetwork-0.1.1.dist-info/top_level.txt
rfnetwork-0.1.1.dist-info/RECORD
rfnetwork-0.1.1.dist-info/licenses/LICENSE.txt
