Metadata-Version: 2.4
Name: rfnetwork
Version: 0.1.1
Summary: rf/microwave network simulation tool
Author-email: Rick Lyon <rlyon14@gmail.com>
License-Expression: MIT
Project-URL: repository, https://github.com/ricklyon/rfnetwork
Keywords: rf,microwave,network,noise
Classifier: Programming Language :: Python
Classifier: Programming Language :: Python :: 3
Requires-Python: >=3.9
License-File: LICENSE.txt
Requires-Dist: numpy>=2.0.0
Requires-Dist: matplotlib
Requires-Dist: scipy
Requires-Dist: np-struct>=0.0.2
Requires-Dist: mpl-markers
Requires-Dist: pyside6
Provides-Extra: dev
Requires-Dist: flake8; extra == "dev"
Requires-Dist: pytest; extra == "dev"
Requires-Dist: parameterized; extra == "dev"
Requires-Dist: ipykernel; extra == "dev"
Requires-Dist: schemdraw; extra == "dev"
Provides-Extra: docs
Requires-Dist: sphinx; extra == "docs"
Requires-Dist: sphinx-rtd-theme==3.0.2; extra == "docs"
Requires-Dist: sphinx-autodoc-typehints==3.2.0; extra == "docs"
Requires-Dist: sphinx-gallery==0.19.0; extra == "docs"
Dynamic: license-file
